eth_bloom/__init__.py
ethereum_bloom-0.4.1.dist-info/DESCRIPTION.rst
ethereum_bloom-0.4.1.dist-info/METADATA
ethereum_bloom-0.4.1.dist-info/RECORD
ethereum_bloom-0.4.1.dist-info/WHEEL
ethereum_bloom-0.4.1.dist-info/metadata.json
ethereum_bloom-0.4.1.dist-info/top_level.txt
