Metadata-Version: 2.0
Name: ethereum-bloom
Version: 0.4.1
Summary: Common utility functions for ethereum codebases.
Home-page: https://github.com/ethereum/ethereum-bloom
Author: Piper Merriam
Author-email: pipermerriam@gmail.com
License: MIT
Keywords: ethereum
Platform: UNKNOWN
Classifier: Intended Audience :: Developers
Classifier: License :: OSI Approved :: MIT License
Classifier: Natural Language :: English
Classifier: Programming Language :: Python :: 2
Classifier: Programming Language :: Python :: 2.7
Classifier: Programming Language :: Python :: 3
Classifier: Programming Language :: Python :: 3.4
Classifier: Programming Language :: Python :: 3.5
